jupyterlab_flake8/__init__.py
jupyterlab_flake8/_version.py
jupyterlab_flake8/labextension/build_log.json
jupyterlab_flake8/labextension/package.json
jupyterlab_flake8/labextension/schemas/jupyterlab-flake8/package.json.orig
jupyterlab_flake8/labextension/schemas/jupyterlab-flake8/plugin.json
jupyterlab_flake8/labextension/static/lib_index_js.9e4bb8b4ed16ff37d433.js
jupyterlab_flake8/labextension/static/lib_index_js.9e4bb8b4ed16ff37d433.js.map
jupyterlab_flake8/labextension/static/lib_index_js.aed4c25accac1bc2a7e8.js
jupyterlab_flake8/labextension/static/lib_index_js.aed4c25accac1bc2a7e8.js.map
jupyterlab_flake8/labextension/static/lib_index_js.e1684daab4071df2a519.js
jupyterlab_flake8/labextension/static/lib_index_js.e1684daab4071df2a519.js.map
jupyterlab_flake8/labextension/static/remoteEntry.122183560c64726875a1.js.map
jupyterlab_flake8/labextension/static/remoteEntry.85f1e113ed3868831ffb.js
jupyterlab_flake8/labextension/static/remoteEntry.85f1e113ed3868831ffb.js.map
jupyterlab_flake8/labextension/static/remoteEntry.aca3f43cf4d5466eae54.js.map
jupyterlab_flake8/labextension/static/style.js
jupyterlab_flake8/labextension/static/style_index_js.ffba65ae5eb5066fb4d7.js
jupyterlab_flake8/labextension/static/style_index_js.ffba65ae5eb5066fb4d7.js.map
jupyterlab_flake8/labextension/static/vendors-node_modules_css-loader_dist_runtime_api_js-node_modules_css-loader_dist_runtime_cssW-926fd9.774fd78a1e21916fe4de.js
jupyterlab_flake8/labextension/static/vendors-node_modules_css-loader_dist_runtime_api_js-node_modules_css-loader_dist_runtime_cssW-926fd9.774fd78a1e21916fe4de.js.map
jupyterlab_flake8-0.7.1.data/data/share/jupyter/labextensions/jupyterlab-flake8/build_log.json
jupyterlab_flake8-0.7.1.data/data/share/jupyter/labextensions/jupyterlab-flake8/install.json
jupyterlab_flake8-0.7.1.data/data/share/jupyter/labextensions/jupyterlab-flake8/package.json
jupyterlab_flake8-0.7.1.dist-info/LICENSE
jupyterlab_flake8-0.7.1.dist-info/METADATA
jupyterlab_flake8-0.7.1.dist-info/WHEEL
jupyterlab_flake8-0.7.1.dist-info/top_level.txt
jupyterlab_flake8-0.7.1.dist-info/RECORD
